{"run_id":"000","rental_date_start":"04/06/2019","rental_date_end":"02/07/2019","agency_name":"Newcastle City Centre","agency_postcode":"NE47JL","screenshot_id":"/tmp/puppeteer/avis/output/NE47JL/avis.co.uk-2019-06-03-duration-28.png","days":28,"rentals":[{"position":"0","size":"small","gps":"no-gps","fuel":"petrol/diesel","transmission":"manual","price":"£420.00"},{"position":"1","size":"small","gps":"no-gps","fuel":"petrol/diesel","transmission":"manual","price":"£440.99"},{"position":"2","size":"medium","gps":"no-gps","fuel":"petrol/diesel","transmission":"manual","price":"£489.98"},{"position":"3","size":"medium","gps":"gps","fuel":"petrol/diesel","transmission":"manual","price":"£587.98"},{"position":"4","size":"medium","gps":"no-gps","fuel":"petrol/diesel","transmission":"manual","price":"£592.72"},{"position":"5","size":"large","gps":"no-gps","fuel":"petrol/diesel","transmission":"manual","price":"£646.84"},{"position":"6","size":"medium","gps":"no-gps","fuel":"petrol/diesel","transmission":"auto","price":"£659.97"},{"position":"7","size":"medium","gps":"no-gps","fuel":"petrol/diesel","transmission":"manual","price":"£686.03"},{"position":"8","size":"medium","gps":"no-gps","fuel":"petrol/diesel","transmission":"auto","price":"£692.99"},{"position":"9","size":"estate","gps":"no-gps","fuel":"petrol/diesel","transmission":"manual","price":"£1,020.78"}],"utag_data":{"pickUpDate":"20190604","pickUpTime":"10:00","pickUpDayName":"Tuesday","pickUpDay":"4","pickUpMonth":"6","pickUpYear":"2019","pickUpLocation":"EJ8","dropOffDate":"20190702","dropOffTime":"10:00","dropOffDayName":"Tuesday","dropOffDay":"2","dropOffMonth":"7","dropOffYear":"2019","dropOffLocation":"EJ8","dropOffLocationName":"Newcastle_Train_Station","dropOffCountry":"GB","rentalDaysFromNow":"1","rentalHoursFromNow":"24","offeredNoOfVehiclesReturned":"10","offeredCurrency":["GBP","GBP","GBP","GBP","GBP","GBP","GBP","GBP","GBP","GBP"],"offeredSize":["Small","Small","Medium","Medium","Medium","Large","Medium","Medium","Medium","Estate"],"offeredModel":["Fiat_500","Citroen_C3","Hyundai_i30","Ford_Focus_with_Sat_Nav","Citroen_Picasso","Volkswagen_Golf","Volkswagen_Golf_Auto","Volkswagen_Passat","Peugeot_3008","Volkswagen_Passat"],"offeredGroup":["A","B","E","M","D","P","I","F","J","H"],"offeredPrices":["420","440.99","489.98","587.98","592.72","646.84","659.97","686.03","692.99","1020.78"],"offeredVehicleGroupSIPPCode":["MBMR","EDMR","CDMR","CCMR","IDMR","PDMR","CDAR","SDMR","SDAR","SWMR"],"offeredVehicleType":["Default","Default","Default","Default","Default","Default","Default","Default","Default","Default"],"offeredPayNowPrices":["420","440.99","489.98","587.98","592.72","646.84","659.97","686.03","692.99","1020.78"],"offeredPayNowCurrency":["GBP","GBP","GBP","GBP","GBP","GBP","GBP","GBP","GBP","GBP"],"offeredPayLaterPrices":["482.96","507.13","563.48","676.12","681.69","743.83","759.03","788.93","796.94","1405.92"],"offeredPayLaterCurrency":["GBP","GBP","GBP","GBP","GBP","GBP","GBP","GBP","GBP","GBP"],"bookingCountry":"UK"}}